deceiver-0.0.1.dist-info/METADATA
deceiver-0.0.1.dist-info/WHEEL
deceiver-0.0.1.dist-info/entry_points.txt
deceiver-0.0.1.dist-info/licenses/LICENSE
deceiver/__init__.py
deceiver/illusions.py
deceiver/log.py
deceiver/records.py
deceiver-0.0.1.dist-info/RECORD
